AUTHORS.rst
CONTRIBUTING.rst
HISTORY.rst
LICENSE
MANIFEST.in
README.rst
setup.cfg
setup.py
sitechantment/__init__.py
sitechantment/sitechantment.py
sitechantment.egg-info/PKG-INFO
sitechantment.egg-info/SOURCES.txt
sitechantment.egg-info/dependency_links.txt
sitechantment.egg-info/entry_points.txt
sitechantment.egg-info/not-zip-safe
sitechantment.egg-info/requires.txt
sitechantment.egg-info/top_level.txt
test/test_sitechantment.py