Metadata-Version: 1.1
Name: sitechantment
Version: 0.1.0
Summary: Check a site for spelling errors
Home-page: https://github.com/mmessmore/sitechantment
Author: Michael Messmore
Author-email: mike@messmore.org
License: BSD
Keywords: sitechantment
Platform: UNKNOWN
Classifier: Development Status :: 2 - Pre-Alpha
Classifier: Intended Audience :: Developers
Classifier: License :: OSI Approved :: MIT License
Classifier: Natural Language :: English
Classifier: Programming Language :: Python :: 2
Classifier: Programming Language :: Python :: 2.6
Classifier: Programming Language :: Python :: 2.7
Classifier: Programming Language :: Python :: 3
Classifier: Programming Language :: Python :: 3.3
Classifier: Programming Language :: Python :: Implementation :: PyPy
